notebook_video_writer/__init__.py
notebook_video_writer/video_writer.py
notebook_video_writer-0.0.5.dist-info/LICENSE
notebook_video_writer-0.0.5.dist-info/METADATA
notebook_video_writer-0.0.5.dist-info/WHEEL
notebook_video_writer-0.0.5.dist-info/top_level.txt
notebook_video_writer-0.0.5.dist-info/RECORD
