Metadata-Version: 2.1
Name: notebook-video-writer
Version: 0.0.5
Summary: Create videos from numpy arrays in a jupyter notebook
Home-page: https://github.com/PWhiddy/notebook-video-writer
Author: None
Author-email: all.cows.like.to.moo@gmail.com
License: MIT
Keywords: video,notebook,jupyter,numpy,interactive
Platform: UNKNOWN
Classifier: Intended Audience :: Developers
Classifier: License :: OSI Approved :: MIT License
Classifier: Natural Language :: English
Classifier: Operating System :: OS Independent
Classifier: Programming Language :: Python :: 3
Classifier: Topic :: Software Development :: Libraries :: Python Modules
Classifier: Topic :: Utilities
Requires-Python: >=3.5
License-File: LICENSE
Requires-Dist: numpy
Requires-Dist: moviepy
